Metadata-Version: 2.4
Name: llama-index-readers-zendesk
Version: 0.4.1
Summary: llama-index readers zendesk integration
Author-email: Your Name <you@example.com>
Maintainer: bbornsztein
License-Expression: MIT
License-File: LICENSE
Keywords: help center,knowledge base,zendesk
Requires-Python: <4.0,>=3.9
Requires-Dist: beautifulsoup4<5,>=4.12.3
Requires-Dist: llama-index-core<0.15,>=0.13.0
Requires-Dist: requests<3,>=2.31.0
